{
  "meta": {
    "format": "httpie",
    "version": "1.0.0",
    "contentType": "workspace",
    "schema": "https://schema.httpie.io/1.0.0.json",
    "docs": "https://httpie.io/r/help/export-from-httpie",
    "source": "HTTPie Desktop 2025.2.0"
  },
  "entry": {
    "name": "Incognito space",
    "icon": {
      "name": "default",
      "color": "gray"
    },
    "collections": [
      {
        "name": "QuoteAPI(Flask-2.Part-2)",
        "icon": {
          "name": "default",
          "color": "gray"
        },
        "auth": {
          "type": "none"
        },
        "requests": [
          {
            "name": "1. Authors / GET List of Authors [Done]",
            "url": "{{HOST}}{{PORT}}/authors",
            "method": "GET",
            "headers": [],
            "queryParams": [],
            "pathParams": [],
            "auth": {
              "type": "inherited"
            },
            "body": {
              "type": "none",
              "file": {
                "name": ""
              },
              "text": {
                "value": "",
                "format": "application/json"
              },
              "form": {
                "isMultipart": false,
                "fields": []
              },
              "graphql": {
                "query": "",
                "variables": ""
              }
            }
          },
          {
            "name": "2. Quotes / GET List of Quotes [Done]",
            "url": "{{HOST}}{{PORT}}/quotes",
            "method": "GET",
            "headers": [],
            "queryParams": [],
            "pathParams": [],
            "auth": {
              "type": "inherited"
            },
            "body": {
              "type": "none",
              "file": {
                "name": ""
              },
              "text": {
                "value": "",
                "format": "application/json"
              },
              "form": {
                "isMultipart": false,
                "fields": []
              },
              "graphql": {
                "query": "",
                "variables": ""
              }
            }
          },
          {
            "name": "3. Authors / GET Author by ID [Done]",
            "url": "{{HOST}}{{PORT}}/authors/2",
            "method": "GET",
            "headers": [],
            "queryParams": [],
            "pathParams": [],
            "auth": {
              "type": "inherited"
            },
            "body": {
              "type": "none",
              "file": {
                "name": ""
              },
              "text": {
                "value": "",
                "format": "application/json"
              },
              "form": {
                "isMultipart": false,
                "fields": []
              },
              "graphql": {
                "query": "",
                "variables": ""
              }
            }
          },
          {
            "name": "4. Quotes / GET Quote by ID [Done]",
            "url": "{{HOST}}{{PORT}}/quotes/6",
            "method": "GET",
            "headers": [],
            "queryParams": [],
            "pathParams": [],
            "auth": {
              "type": "inherited"
            },
            "body": {
              "type": "none",
              "file": {
                "name": ""
              },
              "text": {
                "value": "",
                "format": "application/json"
              },
              "form": {
                "isMultipart": false,
                "fields": []
              },
              "graphql": {
                "query": "",
                "variables": ""
              }
            }
          },
          {
            "name": "5. Authors / Create new Author [Done]",
            "url": "{{HOST}}{{PORT}}/authors",
            "method": "POST",
            "headers": [
              {
                "name": "Content-Type",
                "value": "application/json",
                "enabled": true
              }
            ],
            "queryParams": [],
            "pathParams": [],
            "auth": {
              "type": "inherited"
            },
            "body": {
              "type": "text",
              "file": {
                "name": ""
              },
              "text": {
                "value": "{\n  \"name\": \"Vasiliy\",\n  \"surname\": \"Belov\"\n}",
                "format": "application/json"
              },
              "form": {
                "isMultipart": false,
                "fields": []
              },
              "graphql": {
                "query": "",
                "variables": ""
              }
            }
          },
          {
            "name": "6. Quotes / Create new Quote by Author ID [Done]",
            "url": "{{HOST}}{{PORT}}/authors/3/quotes",
            "method": "POST",
            "headers": [
              {
                "name": "Content-Type",
                "value": "application/json",
                "enabled": true
              }
            ],
            "queryParams": [],
            "pathParams": [],
            "auth": {
              "type": "inherited"
            },
            "body": {
              "type": "text",
              "file": {
                "name": ""
              },
              "text": {
                "value": "  {\n    \"rating\": 4,\n    \"text\": \"Цитата автора с id 3\"\n  }",
                "format": "application/json"
              },
              "form": {
                "isMultipart": false,
                "fields": []
              },
              "graphql": {
                "query": "",
                "variables": ""
              }
            }
          },
          {
            "name": "7. Authors / Delete Author by ID [Done]",
            "url": "{{HOST}}{{PORT}}/authors/3",
            "method": "DELETE",
            "headers": [
              {
                "name": "Content-Type",
                "value": "application/json",
                "enabled": true
              }
            ],
            "queryParams": [],
            "pathParams": [],
            "auth": {
              "type": "inherited"
            },
            "body": {
              "type": "text",
              "file": {
                "name": ""
              },
              "text": {
                "value": "",
                "format": "application/json"
              },
              "form": {
                "isMultipart": false,
                "fields": []
              },
              "graphql": {
                "query": "",
                "variables": ""
              }
            }
          },
          {
            "name": "8. Quotes / Delete Quote by ID [Done]",
            "url": "{{HOST}}{{PORT}}/quotes/6",
            "method": "DELETE",
            "headers": [],
            "queryParams": [],
            "pathParams": [],
            "auth": {
              "type": "inherited"
            },
            "body": {
              "type": "none",
              "file": {
                "name": ""
              },
              "text": {
                "value": "",
                "format": "application/json"
              },
              "form": {
                "isMultipart": false,
                "fields": []
              },
              "graphql": {
                "query": "",
                "variables": ""
              }
            }
          },
          {
            "name": "9. Authors / Edit Author by ID [Done]",
            "url": "{{HOST}}{{PORT}}/authors/3",
            "method": "PUT",
            "headers": [
              {
                "name": "Content-Type",
                "value": "application/json",
                "enabled": true
              }
            ],
            "queryParams": [],
            "pathParams": [],
            "auth": {
              "type": "inherited"
            },
            "body": {
              "type": "text",
              "file": {
                "name": ""
              },
              "text": {
                "value": "{\n  \"name\": \"First\",\n  \"surname\": \"Second\"\n}",
                "format": "application/json"
              },
              "form": {
                "isMultipart": false,
                "fields": []
              },
              "graphql": {
                "query": "",
                "variables": ""
              }
            }
          },
          {
            "name": "10. Quotes / Edit Quote by ID [Done]",
            "url": "{{HOST}}{{PORT}}/quotes/8",
            "method": "PUT",
            "headers": [
              {
                "name": "Content-Type",
                "value": "application/json",
                "enabled": true
              }
            ],
            "queryParams": [],
            "pathParams": [],
            "auth": {
              "type": "inherited"
            },
            "body": {
              "type": "text",
              "file": {
                "name": ""
              },
              "text": {
                "value": "{\n  \"text\": \"C++\",\n  \"rating\": 2\n}",
                "format": "application/json"
              },
              "form": {
                "isMultipart": false,
                "fields": []
              },
              "graphql": {
                "query": "",
                "variables": ""
              }
            }
          },
          {
            "name": "11. Quotes / GET List of Quotes by Author ID [Done]",
            "url": "{{HOST}}{{PORT}}/authors/2/quotes",
            "method": "GET",
            "headers": [],
            "queryParams": [],
            "pathParams": [],
            "auth": {
              "type": "inherited"
            },
            "body": {
              "type": "none",
              "file": {
                "name": ""
              },
              "text": {
                "value": "",
                "format": "application/json"
              },
              "form": {
                "isMultipart": false,
                "fields": []
              },
              "graphql": {
                "query": "",
                "variables": ""
              }
            }
          }
        ]
      }
    ],
    "environments": [
      {
        "name": "Defaults",
        "color": "gray",
        "isDefault": true,
        "isLocalOnly": false,
        "variables": [
          {
            "name": "HOST",
            "value": "http://127.0.0.1",
            "isSecret": false
          },
          {
            "name": "PORT",
            "value": ":5000",
            "isSecret": false
          }
        ]
      }
    ],
    "drafts": []
  }
}